mdkits/__init__.py
mdkits/build_cli/__init__.py
mdkits/build_cli/adsorbate.py
mdkits/build_cli/build_bulk.py
mdkits/build_cli/build_cli.py
mdkits/build_cli/build_interface.py
mdkits/build_cli/build_solution.py
mdkits/build_cli/build_surface.py
mdkits/build_cli/cut_surface.py
mdkits/build_cli/supercell.py
mdkits/build_cli/water.xyz
mdkits/cli/convert.py
mdkits/cli/data.py
mdkits/cli/extract.py
mdkits/cli/plot.py
mdkits/config/__init__.py
mdkits/config/settings.yml
mdkits/dft_cli/.back/pdos.py
mdkits/dft_cli/check_neb.py
mdkits/dft_cli/cube.py
mdkits/dft_cli/dft_cli.py
mdkits/dft_cli/fix.py
mdkits/dft_cli/pdos.py
mdkits/md_cli/angle.py
mdkits/md_cli/density.py
mdkits/md_cli/dipole.py
mdkits/md_cli/hb_distribution.py
mdkits/md_cli/md_cli.py
mdkits/md_cli/monitor.py
mdkits/md_cli/msd.py
mdkits/md_cli/rdf.py
mdkits/md_cli/setting.py
mdkits/md_cli/vac.py
mdkits/md_cli/wrap.py
mdkits/mdkits.py
mdkits/util/.fig_operation.py.swp
mdkits/util/__init__.py
mdkits/util/arg_type.py
mdkits/util/cp2k_input_parsing.py
mdkits/util/encapsulated_ase.py
mdkits/util/encapsulated_mda.py
mdkits/util/fig_operation.py
mdkits/util/numpy_geo.py
mdkits/util/os_operation.py
mdkits/util/out_err.py
mdkits/util/structure_parsing.py
mdkits-1.2.2.dist-info/entry_points.txt
mdkits-1.2.2.dist-info/LICENSE
mdkits-1.2.2.dist-info/METADATA
mdkits-1.2.2.dist-info/WHEEL
mdkits-1.2.2.dist-info/RECORD
