Metadata-Version: 2.3
Name: mdkits
Version: 1.2.2
Summary: kits for md or dft
License: MIT
Keywords: molecular dynamics,density functional theory
Author: jxxcr
Author-email: jixxcr@qq.com
Requires-Python: >=3.11,<4.0
Classifier: License :: OSI Approved :: MIT License
Classifier: Operating System :: OS Independent
Classifier: Programming Language :: Python :: 3
Classifier: Programming Language :: Python :: 3.11
Classifier: Programming Language :: Python :: 3.12
Classifier: Programming Language :: Python :: 3.13
Requires-Dist: Cp2kData (>=0.7.2,<0.8.0)
Requires-Dist: MDAnalysis (>=2.8.0,<3.0.0)
Requires-Dist: ase (>=3.22.1,<4.0.0)
Requires-Dist: click (>=8.1.3,<9.0.0)
Requires-Dist: julia (>=0.6.2,<0.7.0)
Requires-Dist: matplotlib (>=3.9.0,<4.0.0)
Requires-Dist: numpy (>=1.26.4,<2.0.0)
Requires-Dist: pandas (>=2.3.2,<3.0.0)
Requires-Dist: pyyaml (>=6.0.1,<7.0.0)
Requires-Dist: tidynamics (>=1.1.2,<2.0.0)
Project-URL: Repository, https://github.com/jxxcr/mdkits
